pmlab_lite/__init__.py
pmlab_lite/alignments/__init__.py
pmlab_lite/alignments/a_star.py
pmlab_lite/alignments/alignment.py
pmlab_lite/alignments/constants.py
pmlab_lite/alignments/heuristic.py
pmlab_lite/alignments/node.py
pmlab_lite/alignments/variables.py
pmlab_lite/discovery/__init__.py
pmlab_lite/discovery/cut.py
pmlab_lite/discovery/inductive_miner.py
pmlab_lite/discovery/process_tree.py
pmlab_lite/helper/__init__.py
pmlab_lite/helper/graph/__init__.py
pmlab_lite/helper/io/__init__.py
pmlab_lite/helper/io/constants.py
pmlab_lite/helper/io/pnml.py
pmlab_lite/helper/io/xes.py
pmlab_lite/helper/viz/__init__.py
pmlab_lite/helper/viz/dot.py
pmlab_lite/log/__init__.py
pmlab_lite/log/log.py
pmlab_lite/log/transformations.py
pmlab_lite/manipulable/__init__.py
pmlab_lite/manipulable/manipulable.py
pmlab_lite/pn/__init__.py
pmlab_lite/pn/abstract_pn.py
pmlab_lite/pn/pn.py
pmlab_lite/pn/sp.py
pmlab_lite/pn/tn.py
test/__init__.py
test/test_astar.py
test/test_filters.py
test/test_graph.py
test/test_heuristic.py
test/test_pn.py
test/test_updates.py
test/inductive_miner/__init__.py
test/inductive_miner/test_inductive_miner.py
test/inductive_miner/test_process_tree.py
pmlab_lite-0.4.9.1.dist-info/LICENSE
pmlab_lite-0.4.9.1.dist-info/METADATA
pmlab_lite-0.4.9.1.dist-info/WHEEL
pmlab_lite-0.4.9.1.dist-info/top_level.txt
pmlab_lite-0.4.9.1.dist-info/RECORD
