Metadata-Version: 2.1
Name: pmlab-lite
Version: 0.4.9.1
Summary: Process Mining scripting environment
Home-page: https://github.com/pmlab/pmlab-lite
Author: ['Josep Carmona', 'Matthias Weidlich', 'Andrea Burattin', 'jmunozgama', 'Simon Remy', 'Glenn Dittmann']
Author-email: 
License: GPL-3.0
Platform: UNKNOWN
Classifier: Development Status :: 2 - Pre-Alpha
Classifier: Programming Language :: Python :: 3
Requires-Python: >=3.7
License-File: LICENSE
Requires-Dist: numpy
Requires-Dist: graphviz
Requires-Dist: tqdm
Requires-Dist: lxml
Requires-Dist: ortools
